{"us": {"average": {"healer": {"S": [[24, "Discipline Priest"]], "A": [[8, "Restoration Druid"]], "B": [[21, "Holy Paladin"], [19, "Mistweaver Monk"], [32, "Restoration Shaman"]], "C": [[25, "Holy Priest"]], "D": [[11, "Preservation Evoker"]]}, "damage": {"S": [[3, "Havoc Demonhunter"], [2, "Unholy Deathknight"], [36, "Arms Warrior"]], "A": [[23, "Retribution Paladin"], [12, "Beastmastery Hunter"]], "B": [[20, "Windwalker Monk"], [34, "Demonology Warlock"], [35, "Destruction Warlock"], [10, "Devastation Evoker"]], "C": [[14, "Survival Hunter"], [30, "Elemental Shaman"], [26, "Shadow Priest"], [5, "Balance Druid"], [28, "Outlaw Rogue"]], "D": [[15, "Arcane Mage"], [17, "Frost Mage"], [29, "Subtlety Rogue"], [33, "Affliction Warlock"], [9, "Augmentation Evoker"]], "F": [[27, "Assassination Rogue"], [13, "Marksmanship Hunter"], [31, "Enhancement Shaman"], [37, "Fury Warrior"], [16, "Fire Mage"], [1, "Frost Deathknight"], [6, "Feral Druid"]]}}, "top": {"healer": {"S": [[21, "Holy Paladin"], [8, "Restoration Druid"]], "A": [[19, "Mistweaver Monk"], [25, "Holy Priest"]], "B": [[24, "Discipline Priest"]], "C": [[32, "Restoration Shaman"]], "D": [[11, "Preservation Evoker"]]}, "damage": {"S": [[9, "Augmentation Evoker"]], "A": [[30, "Elemental Shaman"], [2, "Unholy Deathknight"], [20, "Windwalker Monk"], [26, "Shadow Priest"]], "B": [[15, "Arcane Mage"], [3, "Havoc Demonhunter"], [23, "Retribution Paladin"], [34, "Demonology Warlock"], [35, "Destruction Warlock"], [36, "Arms Warrior"]], "C": [[5, "Balance Druid"], [10, "Devastation Evoker"], [14, "Survival Hunter"], [28, "Outlaw Rogue"], [12, "Beastmastery Hunter"], [13, "Marksmanship Hunter"], [31, "Enhancement Shaman"]], "D": [[33, "Affliction Warlock"], [16, "Fire Mage"], [6, "Feral Druid"], [29, "Subtlety Rogue"], [17, "Frost Mage"], [37, "Fury Warrior"]], "F": [[27, "Assassination Rogue"], [1, "Frost Deathknight"]]}}}, "eu": {"average": {"healer": {"S": [[24, "Discipline Priest"], [8, "Restoration Druid"]], "A": [[21, "Holy Paladin"]], "B": [[32, "Restoration Shaman"], [19, "Mistweaver Monk"]], "C": [[25, "Holy Priest"]], "D": [[11, "Preservation Evoker"]]}, "damage": {"S": [[3, "Havoc Demonhunter"]], "A": [[36, "Arms Warrior"], [2, "Unholy Deathknight"]], "B": [[20, "Windwalker Monk"], [23, "Retribution Paladin"], [12, "Beastmastery Hunter"], [10, "Devastation Evoker"], [9, "Augmentation Evoker"], [34, "Demonology Warlock"], [35, "Destruction Warlock"]], "C": [[30, "Elemental Shaman"], [14, "Survival Hunter"], [15, "Arcane Mage"], [5, "Balance Druid"], [26, "Shadow Priest"]], "D": [[28, "Outlaw Rogue"], [29, "Subtlety Rogue"], [17, "Frost Mage"], [27, "Assassination Rogue"], [33, "Affliction Warlock"]], "F": [[31, "Enhancement Shaman"], [13, "Marksmanship Hunter"], [37, "Fury Warrior"], [1, "Frost Deathknight"], [16, "Fire Mage"], [6, "Feral Druid"]]}}, "top": {"healer": {"S": [[21, "Holy Paladin"], [8, "Restoration Druid"]], "A": [[25, "Holy Priest"]], "B": [[19, "Mistweaver Monk"], [24, "Discipline Priest"]], "C": [[32, "Restoration Shaman"]], "D": [[11, "Preservation Evoker"]]}, "damage": {"S": [[9, "Augmentation Evoker"]], "A": [[20, "Windwalker Monk"], [30, "Elemental Shaman"], [15, "Arcane Mage"]], "B": [[3, "Havoc Demonhunter"], [2, "Unholy Deathknight"], [26, "Shadow Priest"], [23, "Retribution Paladin"], [10, "Devastation Evoker"], [36, "Arms Warrior"], [16, "Fire Mage"], [14, "Survival Hunter"], [5, "Balance Druid"]], "C": [[35, "Destruction Warlock"], [13, "Marksmanship Hunter"], [34, "Demonology Warlock"], [6, "Feral Druid"], [28, "Outlaw Rogue"], [12, "Beastmastery Hunter"]], "D": [[33, "Affliction Warlock"], [17, "Frost Mage"], [31, "Enhancement Shaman"], [29, "Subtlety Rogue"], [37, "Fury Warrior"]], "F": [[27, "Assassination Rogue"], [1, "Frost Deathknight"]]}}}}